awsbatch/__init__.py
awsbatch/awsbhosts.py
awsbatch/awsbkill.py
awsbatch/awsbout.py
awsbatch/awsbqueues.py
awsbatch/awsbstat.py
awsbatch/awsbsub.py
awsbatch/common.py
awsbatch/utils.py
awsbatch/examples/awsbatch-cli.cfg
aws_parallelcluster_awsbatch_cli-1.5.0.dist-info/METADATA
aws_parallelcluster_awsbatch_cli-1.5.0.dist-info/WHEEL
aws_parallelcluster_awsbatch_cli-1.5.0.dist-info/entry_points.txt
aws_parallelcluster_awsbatch_cli-1.5.0.dist-info/top_level.txt
aws_parallelcluster_awsbatch_cli-1.5.0.dist-info/RECORD
