Metadata-Version: 2.4
Name: aws-parallelcluster-awsbatch-cli
Version: 1.5.0
Summary: AWS ParallelCluster AWS Batch CLI provides a set of commands to manage AWS Batch resources created by ParallelCluster and AWS Batch jobs.
Home-page: https://github.com/aws/aws-parallelcluster
Author: Amazon Web Services
License: Apache License 2.0
Project-URL: Changelog, https://github.com/aws/aws-parallelcluster/blob/develop/awsbatch-cli/CHANGELOG.md
Project-URL: Issue Tracker, https://github.com/aws/aws-parallelcluster/issues
Project-URL: Documentation, https://docs.aws.amazon.com/parallelcluster/
Classifier: Development Status :: 5 - Production/Stable
Classifier: Environment :: Console
Classifier: Programming Language :: Python
Classifier: Programming Language :: Python :: 3
Classifier: Programming Language :: Python :: 3.7
Classifier: Programming Language :: Python :: 3.8
Classifier: Programming Language :: Python :: 3.9
Classifier: Programming Language :: Python :: 3.10
Classifier: Programming Language :: Python :: 3.11
Classifier: Programming Language :: Python :: 3.12
Classifier: Topic :: Scientific/Engineering
Classifier: License :: OSI Approved :: Apache Software License
Requires-Python: >=3.7
Requires-Dist: setuptools
Requires-Dist: boto3>=1.39.4
Requires-Dist: tabulate<=0.8.10,>=0.8.8
Dynamic: author
Dynamic: classifier
Dynamic: description
Dynamic: description-content-type
Dynamic: home-page
Dynamic: license
Dynamic: project-url
Dynamic: requires-dist
Dynamic: requires-python
Dynamic: summary
